autostripe_cli/__init__.py
autostripe_cli/destripe.py
autostripe_cli-0.0.1.dist-info/LICENSE
autostripe_cli-0.0.1.dist-info/METADATA
autostripe_cli-0.0.1.dist-info/WHEEL
autostripe_cli-0.0.1.dist-info/top_level.txt
autostripe_cli-0.0.1.dist-info/RECORD
