Metadata-Version: 2.1
Name: autostripe-cli
Version: 0.0.1
Summary: Automatic command line tool to run pystripe during acquisitions
Home-page: https://github.com/lifecanvastech/
Author: LifeCanvas Technologies
Author-email: joe.gruss@lifecanvastech.com
Classifier: Programming Language :: Python :: 3
Classifier: License :: OSI Approved :: MIT License
Classifier: Operating System :: OS Independent
Requires-Python: >=3.6
License-File: LICENSE
